Search4Faces/__init__.py
Search4Faces/client.py
Search4Faces/exceptions.py
Search4Faces/models.py
Search4Faces/sources.py
Search4Faces-1.0.2.dist-info/LICENSE
Search4Faces-1.0.2.dist-info/METADATA
Search4Faces-1.0.2.dist-info/WHEEL
Search4Faces-1.0.2.dist-info/top_level.txt
Search4Faces-1.0.2.dist-info/RECORD
