Metadata-Version: 2.1
Name: Search4Faces
Version: 1.0.2
Summary: Face recognition via Search4Faces API
Home-page: https://github.com/nikitalm8/Search4FacesAPI
Author: Nikita Minaev
Author-email: <nikita@minaev.su>
Keywords: python,face recognition,search4faces,ai
Classifier: Development Status :: 4 - Beta
Classifier: Intended Audience :: Developers
Classifier: Programming Language :: Python :: 3
Classifier: Operating System :: Unix
Classifier: Operating System :: MacOS :: MacOS X
Classifier: Operating System :: Microsoft :: Windows
License-File: LICENSE
Requires-Dist: httpx
Requires-Dist: pydantic
